odoo/addons/hr_phone/__init__.py
odoo/addons/hr_phone/__manifest__.py
odoo/addons/hr_phone/i18n/es.po
odoo/addons/hr_phone/i18n/hr_phone.pot
odoo/addons/hr_phone/i18n/tr.po
odoo/addons/hr_phone/models/__init__.py
odoo/addons/hr_phone/models/hr_employee.py
odoo/addons/hr_phone/security/ir.model.access.csv
odoo/addons/hr_phone/static/description/icon.png
odoo11_addon_hr_phone-11.0.1.0.0.99.dev3.dist-info/METADATA
odoo11_addon_hr_phone-11.0.1.0.0.99.dev3.dist-info/RECORD
odoo11_addon_hr_phone-11.0.1.0.0.99.dev3.dist-info/WHEEL
odoo11_addon_hr_phone-11.0.1.0.0.99.dev3.dist-info/top_level.txt
